.DS_Store
.gitignore
.virtualenv
AUTHORS
Gemfile
Guardfile
LICENSE
MANIFEST.in
NEWS
README
entry-points.ini
fabfile.py
requirements-dev.txt
requirements.txt
setup.py
csat/__init__.py
csat/client.py
csat/logging.py
csat/paths.py
csat/protocols.py
csat/queue.py
csat/tasks.py
csat/utils.py
csat.egg-info/PKG-INFO
csat.egg-info/SOURCES.txt
csat.egg-info/dependency_links.txt
csat.egg-info/entry_points.txt
csat.egg-info/requires.txt
csat.egg-info/top_level.txt
csat/acquisition/__init__.py
csat/acquisition/admin.py
csat/acquisition/assets.py
csat/acquisition/base.py
csat/acquisition/forms.py
csat/acquisition/models.py
csat/acquisition/runner.py
csat/acquisition/server.py
csat/acquisition/urls.py
csat/acquisition/views.py
csat/acquisition/assets/coffeescripts/acquisition.coffee
csat/acquisition/assets/sass/acquisition/screen.sass
csat/acquisition/migrations/0001_initial.py
csat/acquisition/migrations/0002_auto__add_field_acquisitionsessionconfig_temporary.py
csat/acquisition/migrations/0003_auto__add_field_acquisitionsessionconfig_created.py
csat/acquisition/migrations/0004_auto__add_field_acquisitionsessionconfig_started__add_field_acquisitio.py
csat/acquisition/migrations/0005_auto__del_unique_datacollectorconfig_running_instance_id.py
csat/acquisition/migrations/0006_auto__add_field_acquisitionsessionconfig_database.py
csat/acquisition/migrations/0007_auto__add_field_datacollectorconfig_result_id__add_field_datacollector.py
csat/acquisition/migrations/0008_auto__del_field_datacollectorconfig_result__add_field_datacollectorcon.py
csat/acquisition/migrations/0009_auto__del_field_datacollectorconfig_received__add_field_datacollectorc.py
csat/acquisition/migrations/0010_auto__del_field_acquisitionsessionconfig_database.py
csat/acquisition/migrations/0011_auto__add_field_acquisitionsessionconfig_graph.py
csat/acquisition/migrations/0012_auto__add_field_acquisitionsessionconfig_thumbnail.py
csat/acquisition/migrations/0013_auto__add_field_acquisitionsessionconfig_dark_thumbnail.py
csat/acquisition/migrations/0014_auto__del_field_acquisitionsessionconfig_dark_thumbnail__add_field_acq.py
csat/acquisition/migrations/__init__.py
