Metadata-Version: 1.0
Name: csat
Version: 0.3
Summary: Complex Software Analysis Toolkit
Home-page: https://github.com/GaretJax/csat
Author: Jonathan Stoppani
Author-email: jonathan@stoppani.name
License: MIT
Platform: UNKNOWN
